dataprocessing/__init__.py
dataprocessing/data-processing-functions.py
dataprocessing/datafunctions.py
imsciencesdataprocessing/__init__.py
imsciencesdataprocessing/datafunctions.py
imsdataprocessing/__init__.py
imsdataprocessing/datafunctions.py
imsciencesdataprocessing-0.0.1.dist-info/METADATA
imsciencesdataprocessing-0.0.1.dist-info/WHEEL
imsciencesdataprocessing-0.0.1.dist-info/top_level.txt
imsciencesdataprocessing-0.0.1.dist-info/RECORD
